door_toolkit/__init__.py
door_toolkit/__main__.py
door_toolkit/cli.py
door_toolkit/cli_flywire.py
door_toolkit/cli_neural.py
door_toolkit/cli_pathways.py
door_toolkit/encoder.py
door_toolkit/extractor.py
door_toolkit/preflight.py
door_toolkit/utils.py
door_toolkit/connectomics/__init__.py
door_toolkit/connectomics/config.py
door_toolkit/connectomics/data_loader.py
door_toolkit/connectomics/network_builder.py
door_toolkit/connectomics/pathway_analysis.py
door_toolkit/connectomics/statistics.py
door_toolkit/connectomics/visualization.py
door_toolkit/data/__init__.py
door_toolkit/data/receptor_groups.py
door_toolkit/data/sequence_dataset.py
door_toolkit/data/training_receptor_validator.py
door_toolkit/flywire/__init__.py
door_toolkit/flywire/community_labels.py
door_toolkit/flywire/mapper.py
door_toolkit/flywire/mushroom_body_tracer.py
door_toolkit/flywire/orn_database_tools.py
door_toolkit/flywire/spatial_analysis.py
door_toolkit/integration/__init__.py
door_toolkit/integration/door_to_flywire_mapping.py
door_toolkit/integration/door_utils.py
door_toolkit/integration/integrator.py
door_toolkit/integration/mapping_accounting.py
door_toolkit/integration/odorant_mapper.py
door_toolkit/integration/odorant_mapping.py
door_toolkit/integration/orn_identifier.py
door_toolkit/integration/receptor_identifier.py
door_toolkit/integration/receptor_inventory.py
door_toolkit/neural/__init__.py
door_toolkit/neural/concentration_models.py
door_toolkit/neural/preprocessor.py
door_toolkit/neural/sparse_encoding.py
door_toolkit/neural/static_door_recurrent_circuit.py
door_toolkit/pathways/__init__.py
door_toolkit/pathways/analyzer.py
door_toolkit/pathways/behavioral_prediction.py
door_toolkit/pathways/blocking_experiments.py
door_python_toolkit-1.0.1.dist-info/METADATA
door_python_toolkit-1.0.1.dist-info/WHEEL
door_python_toolkit-1.0.1.dist-info/entry_points.txt
door_python_toolkit-1.0.1.dist-info/licenses/LICENSE
door_python_toolkit-1.0.1.dist-info/RECORD
