Metadata-Version: 2.4
Name: DoOR-python-toolkit
Version: 1.0.1
Summary: Comprehensive Python toolkit for Drosophila olfactory research: DoOR database integration, FlyWire connectomics, mushroom body circuit validation, and LASSO behavioral prediction.
Project-URL: Homepage, https://github.com/colehanan1/DoOR-python-toolkit
Project-URL: Documentation, https://door-python-toolkit.readthedocs.io
Project-URL: Repository, https://github.com/colehanan1/DoOR-python-toolkit
Project-URL: Issues, https://github.com/colehanan1/DoOR-python-toolkit/issues
Project-URL: Changelog, https://github.com/colehanan1/DoOR-python-toolkit/blob/main/CHANGELOG.md
Author-email: Cole Hanan <your.email@example.com>
License: MIT License
License-File: LICENSE
Keywords: behavioral-prediction,bioinformatics,connectomics,door,drosophila,flywire,lasso,machine-learning,mushroom-body,neural-network,neuroscience,odorant,olfaction,optogenetics,receptor
Classifier: Development Status :: 5 - Production/Stable
Classifier: Intended Audience :: Science/Research
Classifier: License :: OSI Approved :: MIT License
Classifier: Operating System :: OS Independent
Classifier: Programming Language :: Python :: 3
Classifier: Programming Language :: Python :: 3.8
Classifier: Programming Language :: Python :: 3.9
Classifier: Programming Language :: Python :: 3.10
Classifier: Programming Language :: Python :: 3.11
Classifier: Programming Language :: Python :: 3.12
Classifier: Topic :: Scientific/Engineering :: Artificial Intelligence
Classifier: Topic :: Scientific/Engineering :: Bio-Informatics
Requires-Python: >=3.8
Requires-Dist: matplotlib>=3.5.0
Requires-Dist: networkx>=2.8
Requires-Dist: numpy>=1.21.0
Requires-Dist: pandas>=1.5.0
Requires-Dist: pyarrow>=12.0.0
Requires-Dist: scikit-learn>=1.1.0
Requires-Dist: scipy>=1.9.0
Requires-Dist: tqdm>=4.64.0
Provides-Extra: all
Requires-Dist: h5py>=3.7.0; extra == 'all'
Requires-Dist: plotly>=5.11.0; extra == 'all'
Requires-Dist: pyreadr>=0.4.7; extra == 'all'
Requires-Dist: python-louvain>=0.16; extra == 'all'
Requires-Dist: seaborn>=0.11.0; extra == 'all'
Requires-Dist: torch>=2.0.0; extra == 'all'
Requires-Dist: trimesh>=3.15.0; extra == 'all'
Provides-Extra: connectomics
Requires-Dist: python-louvain>=0.16; extra == 'connectomics'
Requires-Dist: seaborn>=0.11.0; extra == 'connectomics'
Provides-Extra: dev
Requires-Dist: black>=23.0.0; extra == 'dev'
Requires-Dist: flake8>=6.0.0; extra == 'dev'
Requires-Dist: mypy>=1.0.0; extra == 'dev'
Requires-Dist: pytest-cov>=4.0.0; extra == 'dev'
Requires-Dist: pytest>=7.0.0; extra == 'dev'
Requires-Dist: tomli>=2.0.1; (python_version < '3.11') and extra == 'dev'
Provides-Extra: docs
Requires-Dist: sphinx-rtd-theme>=1.2.0; extra == 'docs'
Requires-Dist: sphinx>=6.0.0; extra == 'docs'
Provides-Extra: extract
Requires-Dist: pyreadr>=0.4.7; extra == 'extract'
Provides-Extra: flywire
Requires-Dist: plotly>=5.11.0; extra == 'flywire'
Requires-Dist: seaborn>=0.11.0; extra == 'flywire'
Provides-Extra: h5
Requires-Dist: h5py>=3.7.0; extra == 'h5'
Provides-Extra: spatial
Requires-Dist: trimesh>=3.15.0; extra == 'spatial'
Provides-Extra: torch
Requires-Dist: torch>=2.0.0; extra == 'torch'
